cloudpss/__init__.py
cloudpss/verify.py
cloudpss/version.py
cloudpss/asyncio/__init__.py
cloudpss/asyncio/job/__init__.py
cloudpss/asyncio/job/job.py
cloudpss/asyncio/job/messageStreamReceiver.py
cloudpss/asyncio/job/messageStreamSender.py
cloudpss/asyncio/model/__init__.py
cloudpss/asyncio/model/model.py
cloudpss/asyncio/model/revision.py
cloudpss/asyncio/model/topology.py
cloudpss/asyncio/utils/AsyncIterable.py
cloudpss/asyncio/utils/__init__.py
cloudpss/asyncio/utils/httpAsyncRequest.py
cloudpss/dslab/__init__.py
cloudpss/dslab/dataManageModel.py
cloudpss/dslab/dslab.py
cloudpss/dslab/financialAnalysisModel.py
cloudpss/dslab/files/__init__.py
cloudpss/dslab/files/curveData.py
cloudpss/dslab/files/files.py
cloudpss/function/__init__.py
cloudpss/function/function.py
cloudpss/function/functionExecution.py
cloudpss/function/job.py
cloudpss/ieslab/DataManageModel.py
cloudpss/ieslab/EvaluationModel.py
cloudpss/ieslab/IESLabOpt.py
cloudpss/ieslab/IESLabPlan.py
cloudpss/ieslab/IESLabSimulation.py
cloudpss/ieslab/PlanModel.py
cloudpss/ieslab/__init__.py
cloudpss/job/TemplateCompiler.py
cloudpss/job/TemplateManager.py
cloudpss/job/__init__.py
cloudpss/job/job.py
cloudpss/job/jobReceiver.py
cloudpss/job/messageStreamReceiver.py
cloudpss/job/messageStreamSender.py
cloudpss/job/result/EMTResult.py
cloudpss/job/result/IESLabSimulationResult.py
cloudpss/job/result/IESLabTypicalDayResult.py
cloudpss/job/result/IESResult.py
cloudpss/job/result/PowerFlowResult.py
cloudpss/job/result/__init__.py
cloudpss/job/result/result.py
cloudpss/model/__init__.py
cloudpss/model/jobDefinitions.py
cloudpss/model/model.py
cloudpss/model/revision.py
cloudpss/model/topology.py
cloudpss/model/implements/__init__.py
cloudpss/model/implements/component.py
cloudpss/model/implements/diagram.py
cloudpss/model/implements/implement.py
cloudpss/project/__init__.py
cloudpss/project/project.py
cloudpss/runner/DSLabResult.py
cloudpss/runner/IESLabEvaluationResult.py
cloudpss/runner/IESLabPlanResult.py
cloudpss-4.5.27.dist-info/METADATA
cloudpss-4.5.27.dist-info/WHEEL
cloudpss-4.5.27.dist-info/top_level.txt
cloudpss-4.5.27.dist-info/RECORD
