Metadata-Version: 2.1
Name: cloudpss
Version: 4.5.27
Summary: cloudpss sdk
Home-page: https://www.cloudpss.net
Author: cloudpss
Author-email: zhangdaming@cloudpss.net
License: MIT Licence
Keywords: cloudpss,cloudpss-sdk
Platform: any
Requires-Python: >=3.7
Requires-Dist: cffi
Requires-Dist: cryptography
Requires-Dist: cycler
Requires-Dist: pycparser
Requires-Dist: PyJWT
Requires-Dist: numpy
Requires-Dist: PyYAML
Requires-Dist: requests
Requires-Dist: websocket-client >=1.4.0
Requires-Dist: pytz
Requires-Dist: deprecated
Requires-Dist: py-ubjson
Requires-Dist: aiohttp
Requires-Dist: zstandard
